README.rst
setup.py
docket/__init__.py
docket/cli.py
docket/ext_csv.py
docket/ext_json.py
docket/grants.py
docket/orders.py
docket/slipopinions.py
nyt_docket.egg-info/PKG-INFO
nyt_docket.egg-info/SOURCES.txt
nyt_docket.egg-info/dependency_links.txt
nyt_docket.egg-info/entry_points.txt
nyt_docket.egg-info/requires.txt
nyt_docket.egg-info/top_level.txt