Metadata-Version: 1.1
Name: nyt-docket
Version: 0.0.10
Summary: Python client for parsing SCOTUS cases from the granted/noted and orders dockets.
Home-page: https://github.com/newsdev/nyt-docket
Author: Jeremy Bowers
Author-email: jeremy.bowers@nytimes.com
License: Apache License 2.0
Keywords: SCOTUS data parsing scraping legal law court
Platform: UNKNOWN
Classifier: Development Status :: 3 - Alpha
Classifier: Intended Audience :: Developers
Classifier: Programming Language :: Python
Classifier: Topic :: Software Development :: Libraries :: Python Modules
